odoo/addons/account_banking_ach_base/README.rst
odoo/addons/account_banking_ach_base/__init__.py
odoo/addons/account_banking_ach_base/__manifest__.py
odoo/addons/account_banking_ach_base/i18n/account_banking_ach_base.pot
odoo/addons/account_banking_ach_base/models/__init__.py
odoo/addons/account_banking_ach_base/models/account_banking_mandate.py
odoo/addons/account_banking_ach_base/models/account_move.py
odoo/addons/account_banking_ach_base/models/account_payment_method.py
odoo/addons/account_banking_ach_base/models/account_payment_order.py
odoo/addons/account_banking_ach_base/models/res_bank.py
odoo/addons/account_banking_ach_base/models/res_company.py
odoo/addons/account_banking_ach_base/readme/CONTRIBUTORS.md
odoo/addons/account_banking_ach_base/readme/DESCRIPTION.md
odoo/addons/account_banking_ach_base/readme/USAGE.md
odoo/addons/account_banking_ach_base/static/description/icon.png
odoo/addons/account_banking_ach_base/static/description/index.html
odoo/addons/account_banking_ach_base/views/account_banking_mandate.xml
odoo/addons/account_banking_ach_base/views/account_move.xml
odoo/addons/account_banking_ach_base/views/res_bank.xml
odoo/addons/account_banking_ach_base/views/res_company.xml
odoo_addon_account_banking_ach_base-18.0.1.0.0.2.dist-info/METADATA
odoo_addon_account_banking_ach_base-18.0.1.0.0.2.dist-info/WHEEL
odoo_addon_account_banking_ach_base-18.0.1.0.0.2.dist-info/top_level.txt
odoo_addon_account_banking_ach_base-18.0.1.0.0.2.dist-info/RECORD
