Metadata-Version: 2.1
Name: odoo-addon-account_banking_ach_base
Version: 18.0.1.0.0.2
Requires-Python: >=3.10
Requires-Dist: ach
Requires-Dist: odoo-addon-account_banking_mandate==18.0.*
Requires-Dist: odoo-addon-account_payment_order==18.0.*
Requires-Dist: odoo-addon-l10n_us_partner_legal_number==18.0.*
Requires-Dist: odoo==18.0.*
Requires-Dist: python-stdnum
Summary: Add fields required for North American Banking & Financials
Home-page: https://github.com/OCA/l10n-usa
License: AGPL-3
Author: Thinkwell Designs, Odoo Community Association (OCA)
Author-email: support@odoo-community.org
Classifier: Programming Language :: Python
Classifier: Framework :: Odoo
Classifier: Framework :: Odoo :: 18.0
Classifier: License :: OSI Approved :: GNU Affero General Public License v3
